plain_client/__init__.py
plain_client/__version__.py
plain_client/add_customer_to_customer_groups.py
plain_client/add_customer_to_tenants.py
plain_client/add_labels.py
plain_client/add_members_to_tier.py
plain_client/archive_label_type.py
plain_client/assign_thread.py
plain_client/async_base_client.py
plain_client/base_model.py
plain_client/change_thread_priority.py
plain_client/client.py
plain_client/companies.py
plain_client/create_attachment_upload_url.py
plain_client/create_customer_card_config.py
plain_client/create_customer_event.py
plain_client/create_knowledge_source.py
plain_client/create_label_type.py
plain_client/create_note.py
plain_client/create_thread.py
plain_client/create_thread_event.py
plain_client/create_webhook_target.py
plain_client/customer_by_email.py
plain_client/customer_by_external_id.py
plain_client/customer_by_id.py
plain_client/customer_customer_groups.py
plain_client/customer_group_by_id.py
plain_client/customer_groups.py
plain_client/customer_tenants.py
plain_client/customers.py
plain_client/delete_customer.py
plain_client/delete_customer_card_config.py
plain_client/delete_thread_field.py
plain_client/delete_webhook_target.py
plain_client/enums.py
plain_client/exceptions.py
plain_client/fragments.py
plain_client/index_document.py
plain_client/input_types.py
plain_client/label_type.py
plain_client/label_types.py
plain_client/mark_thread_as_done.py
plain_client/mark_thread_as_todo.py
plain_client/my_workspace.py
plain_client/py.typed
plain_client/remove_customer_from_customer_groups.py
plain_client/remove_customer_from_tenants.py
plain_client/remove_labels.py
plain_client/remove_members_from_tier.py
plain_client/reply_to_email.py
plain_client/reply_to_thread.py
plain_client/search_companies.py
plain_client/search_tenants.py
plain_client/send_customer_chat.py
plain_client/send_new_email.py
plain_client/set_customer_tenants.py
plain_client/snooze_thread.py
plain_client/tenant.py
plain_client/tenants.py
plain_client/thread.py
plain_client-0.0.3.dist-info/METADATA
plain_client-0.0.3.dist-info/WHEEL
plain_client-0.0.3.dist-info/licenses/LICENSE
plain_client-0.0.3.dist-info/RECORD
