Metadata-Version: 2.4
Name: plain-client
Version: 0.0.3
Summary: A Python client for Plain GraphQL API
Project-URL: Documentation, https://frankie567.github.io/plain-client/
Project-URL: Source, https://github.com/frankie567/plain-client
Author-email: plain-client <fvoron@gmail.com>
License-File: LICENSE
Classifier: License :: OSI Approved :: MIT License
Classifier: Programming Language :: Python :: 3 :: Only
Classifier: Programming Language :: Python :: 3.9
Classifier: Programming Language :: Python :: 3.10
Classifier: Programming Language :: Python :: 3.11
Classifier: Programming Language :: Python :: 3.12
Classifier: Programming Language :: Python :: 3.13
Requires-Python: >=3.9
Requires-Dist: graphql-core
Requires-Dist: httpx
Requires-Dist: pydantic<3.0.0,>=2.0.0
